CHANGES.txt
MANIFEST.in
README.txt
setup.py
libopencore/__init__.py
libopencore/auth.py
libopencore/deliverance.xml
libopencore/deliverance_middleware.py
libopencore/http_proxy.py
libopencore/import_utils.py
libopencore/mock_opencore.py
libopencore/query_project.py
libopencore/transcluder_middleware.py
libopencore/wsgi.py
libopencore.egg-info/PKG-INFO
libopencore.egg-info/SOURCES.txt
libopencore.egg-info/dependency_links.txt
libopencore.egg-info/entry_points.txt
libopencore.egg-info/not-zip-safe
libopencore.egg-info/requires.txt
libopencore.egg-info/top_level.txt