Metadata-Version: 1.0
Name: libopencore
Version: 0.7.1
Summary: a library of functions for connecting external apps to/from opencore
Home-page: UNKNOWN
Author: Ethan Jucovy
Author-email: opencore-dev@lists.coactivate.org
License: GPL
Platform: UNKNOWN
